scram_client/__init__.py
scram_client/__main__.py
scram_client/cli.py
scram_client-0.5.dist-info/LICENSE
scram_client-0.5.dist-info/METADATA
scram_client-0.5.dist-info/WHEEL
scram_client-0.5.dist-info/entry_points.txt
scram_client-0.5.dist-info/top_level.txt
scram_client-0.5.dist-info/zip-safe
scram_client-0.5.dist-info/RECORD
