Metadata-Version: 2.1
Name: scram-client
Version: 0.5
Summary: A client for use with the SCRAM black hole routing software.
Author: Vlad Grigorescu, Sam Oehlert
Author-email: Michael Dopheide <dopheide@es.net>
Project-URL: homepage, https://github.com/esnet-security/scram-client
Classifier: Programming Language :: Python :: 3
Classifier: Operating System :: OS Independent
Requires-Python: >=3.7
License-File: LICENSE
Requires-Dist: requests
Requires-Dist: prometheus-client
Requires-Dist: walrus
